bebi103/.gitignore
bebi103/__init__.py
bebi103/az_utils.py
bebi103/bootstrap.py
bebi103/gp.py
bebi103/hv.py
bebi103/image.py
bebi103/stan.py
bebi103/stan_int_rng.stan
bebi103/stan_real_rng.stan
bebi103/utils.py
bebi103/viz.py
bebi103/deprecated/bootstrap_deprecated.py
bebi103/deprecated/emcee.py
bebi103/deprecated/hotdists.py
bebi103/deprecated/make_hot.py
bebi103/deprecated/pm.py
bebi103/deprecated/stan_deprecated.py
bebi103/deprecated/tools.py
bebi103/deprecated/viz_deprecated.py
bebi103/stan_include/gp_one_dimensional.stanfunctions
bebi103/stan_include/inv_gaussian.stanfunctions
bebi103/stan_include/utils.stanfunctions
bebi103-0.1.28.dist-info/licenses/LICENSE.md
bebi103-0.1.28.dist-info/METADATA
bebi103-0.1.28.dist-info/WHEEL
bebi103-0.1.28.dist-info/top_level.txt
bebi103-0.1.28.dist-info/RECORD
