Metadata-Version: 2.4
Name: bebi103
Version: 0.1.28
Summary: Python utilities for the Caltech course BE/Bi 103: Data Analysis in the Biological Sciences.
Home-page: https://github.com/justinbois/bebi103
Download-URL: https://github.com/justinbois/bebi103/tarball/0.1.28
Author: Justin Bois
Author-email: bois@caltech.edu
License: BSD
Keywords: GitHub,Python,Instruction,Biology
Classifier: Development Status :: 3 - Alpha
Classifier: Intended Audience :: Developers
Classifier: Programming Language :: Python :: 3
License-File: LICENSE.md
Requires-Dist: cmdstanpy>=1.0.0
Requires-Dist: contourpy
Requires-Dist: numpy
Requires-Dist: numba
Requires-Dist: xarray
Requires-Dist: scipy
Requires-Dist: pandas
Requires-Dist: polars
Requires-Dist: tqdm
Requires-Dist: bokeh>=3.4.0
Requires-Dist: matplotlib
Requires-Dist: arviz>=0.16.0
Requires-Dist: colorcet
Requires-Dist: holoviews
Dynamic: author
Dynamic: author-email
Dynamic: classifier
Dynamic: description
Dynamic: download-url
Dynamic: home-page
Dynamic: keywords
Dynamic: license
Dynamic: license-file
Dynamic: requires-dist
Dynamic: summary
